{
    "metadata" : {
                    "id": "a_001",
                    "class": "Α",
                    "title" : "Οδική ασφάλεια 01",
                    "subtitle" : "Συμπλήρωσε τις παρακάτω προτάσεις με τις λέξεις που δίνονται",
                    "shuffle_sentences" : "false",
                    "send_score" : "false"
                },
    "sentences" : {
                    "0" :   { 
                                "sentence" : "Δύο Η/Υ που ανήκουν στον ίδιο δίκτυο, μπορούν να *** μεταξύ τους.",
                                "missing_word" : "επικοινωνούν"
                            },
                    "1" :   {
                                "sentence" : "Στην πιο απλή περίπτωση δικτύου, δύο Η/Υ συνδέονται μεταξύ τους με την χρήση ενός ***.",
                                "missing_word" : "καλωδίου"
                            },
                    "2" :   {
                                "sentence" : "Υπάρχουν δύο ειδών δίκτυα: τα ενσύρματα και τα ***.",
                                "missing_word" : "ασύρματα"
                            },
                    "3" :   {
                                "sentence" : "Ο κεντρικός Η/Υ ενός δικτύου πολλών Η/Υ ονομάζεται server ή στα Ελληνικά ***.",
                                "missing_word" : "εξυπηρετητής"
                            },
                    "4" :   {
                                "sentence" : "Το δια-δίκτυο (internet) διασυνδέει έναν μεγάλο αριθμό μικρότερων *** μεταξύ τους.",
                                "missing_word" : "δικτύων"
                            }
                }   
}
